<?xml version="1.0" encoding="UTF-8"?>
<!--
  SPDX-License-Identifier: AGPL-3.0-or-later

  Per-user GSettings schema for paladin-gtk.  The reverse-DNS id
  matches `paladin_gtk::APP_ID` (also the gio::Application id and
  the .desktop file basename) and the path is the canonical
  `/<id-as-path>/` form so dconf groups the keys under
  `org/tamx/Paladin/Gui/`.

  Keys here describe per-user GUI display preferences only — never
  vault behavior.  Vault-bound preferences (auto-lock, clipboard
  auto-clear, …) live in `paladin_core::VaultSettings` and are
  persisted inside the vault payload per DESIGN §4.7.
-->
<schemalist>
  <schema id="org.tamx.Paladin.Gui" path="/org/tamx/Paladin/Gui/">
    <key name="show-section-headers" type="b">
      <default>false</default>
      <summary>Show issuer section headers</summary>
      <description>
        When enabled, the account list groups consecutive rows by
        issuer and renders a small heading above the first row of
        each issuer run.  Vault insertion order is preserved — rows
        are never reordered for grouping.  Disabled by default so
        the list stays compact.
      </description>
    </key>
    <key name="show-column-headers" type="b">
      <default>true</default>
      <summary>Show account list column headers</summary>
      <description>
        When enabled, the account list shows the column header strip
        (Account / Code / Time / Copy / Menu) at the top of the
        list.  Enabled by default so the ColumnView shape is
        labelled out of the box; users who prefer a compact list
        can hide it from the Display preferences group.
      </description>
    </key>
    <key name="show-next-code-column" type="b">
      <default>true</default>
      <summary>Show the next-code column on TOTP rows</summary>
      <description>
        When enabled, the account list shows a "Next" column between
        the Code and Time columns; on TOTP rows it renders the
        upcoming code prefixed with `↪`, and clicking the cell (or
        pressing Ctrl+Shift+C with the row selected) copies that
        upcoming code with a toast reading "Next code copied, valid
        in Xs".  HOTP and section rows render an empty cell.  The
        column hides altogether if the rendered list has no TOTP
        rows even when this key is true, so the column never sits
        empty.  Enabled by default per IMPLEMENTATION_PLAN_04
        "Next-code column implementation"; users who prefer a more
        compact list can hide it from the Display preferences group.
      </description>
    </key>
  </schema>
</schemalist>
